nlsh/__init__.py
nlsh/cli.py
nlsh/context.py
nlsh/history.py
nlsh/langgraph_llm.py
nlsh/llm.py
nlsh/shell.py
nlsh/streaming.py
nlsh/tools.py
nlsh/utils.py
nlsh_ai-0.1.7.dist-info/LICENSE
nlsh_ai-0.1.7.dist-info/METADATA
nlsh_ai-0.1.7.dist-info/WHEEL
nlsh_ai-0.1.7.dist-info/entry_points.txt
nlsh_ai-0.1.7.dist-info/RECORD
