Metadata-Version: 2.3
Name: nlsh-ai
Version: 0.1.7
Summary: Natural Language Shell - AI-augmented command line interface
License: MIT
Keywords: ai,shell,cli,llm,natural-language,command-line
Author: Isaac Harrison Gutekunst
Author-email: isaac@supercortex.io
Requires-Python: >=3.9,<4.0
Classifier: Development Status :: 4 - Beta
Classifier: Intended Audience :: Developers
Classifier: Intended Audience :: System Administrators
Classifier: License :: OSI Approved :: MIT License
Classifier: Operating System :: OS Independent
Classifier: Programming Language :: Python :: 3
Classifier: Programming Language :: Python :: 3.9
Classifier: Programming Language :: Python :: 3.10
Classifier: Programming Language :: Python :: 3.11
Classifier: Programming Language :: Python :: 3.12
Classifier: Programming Language :: Python :: 3.13
Classifier: Topic :: Software Development :: Libraries :: Python Modules
Classifier: Topic :: System :: Shells
Classifier: Topic :: Terminals
Requires-Dist: langchain-anthropic (==0.3.13)
Requires-Dist: langchain-core (==0.3.61)
Requires-Dist: langchain-openai (==0.3.18)
Requires-Dist: langgraph (==0.4.7)
Requires-Dist: openai (==1.82.0)
Requires-Dist: prompt-toolkit (==3.0.51)
Requires-Dist: python-dotenv (==1.1.0)
Requires-Dist: rich (==13.9.4)
Requires-Dist: typer (==0.12.5)
Project-URL: Documentation, https://github.com/igutekunst/nlsh
Project-URL: Homepage, https://github.com/igutekunst/nlsh
Project-URL: Repository, https://github.com/igutekunst/nlsh
